README.md
setup.py
portmin/__init__.py
portmin/optimization.pxd
portmin/optimization.pyx
portmin/toms611.c
portmin.egg-info/PKG-INFO
portmin.egg-info/SOURCES.txt
portmin.egg-info/dependency_links.txt
portmin.egg-info/not-zip-safe
portmin.egg-info/requires.txt
portmin.egg-info/top_level.txt