Metadata-Version: 2.1
Name: portmin
Version: 1.0.6
Summary: PORT unconstrained optimization routines wrapper.
Home-page: https://bitbucket.org/herrberg/portmin/
Author: Meshcheryakov A. Georgy
Author-email: metsheryakov_ga@spbstu.ru
License: UNKNOWN
Platform: UNKNOWN
Classifier: Programming Language :: Python :: 3
Classifier: License :: OSI Approved :: MIT License
Classifier: Operating System :: OS Independent
